sqlalchemy_pytest/__init__.py
sqlalchemy_pytest/_utils.py
sqlalchemy_pytest/database.py
sqlalchemy_pytest-0.3.2.post1.dist-info/WHEEL
sqlalchemy_pytest-0.3.2.post1.dist-info/METADATA
sqlalchemy_pytest-0.3.2.post1.dist-info/RECORD
