Metadata-Version: 2.1
Name: sqlalchemy-pytest
Version: 0.3.2.post1
License: MIT
Author-email: Doctor <thirvondukr@gmail.com>
Requires-Python: >=3.10
Requires-Dist: anyio>=3.6.2
